rtraflow/__init__.py
rtraflow/connector.py
rtraflow-0.4.dist-info/METADATA
rtraflow-0.4.dist-info/WHEEL
rtraflow-0.4.dist-info/top_level.txt
rtraflow-0.4.dist-info/RECORD
