Metadata-Version: 2.1
Name: rtraflow
Version: 0.4
Summary: Package for RTRAConnect functionality
Home-page: https://github.com/uditakhourii/RTRAConnect
Author: Udit Raj
Author-email: udit_2312res708@iitp.ac.in
Classifier: Programming Language :: Python :: 3
Classifier: License :: OSI Approved :: MIT License
Classifier: Operating System :: OS Independent
Requires-Dist: requests
